asyncio_task_manager/__about__.py
asyncio_task_manager/__init__.py
asyncio_task_manager/taskmanager.py
asyncio_task_manager-1.0.0.dist-info/METADATA
asyncio_task_manager-1.0.0.dist-info/WHEEL
asyncio_task_manager-1.0.0.dist-info/licenses/LICENSE.txt
asyncio_task_manager-1.0.0.dist-info/RECORD
