Metadata-Version: 2.1
Name: asyncio-task-manager
Version: 1.0.0
Summary: A Python library for managing asynchronous task dependencies.
Project-URL: Documentation, https://github.com/peterrauscher/asyncio-task-manager#readme
Project-URL: Issues, https://github.com/peterrauscher/asyncio-task-manager/issues
Project-URL: Source, https://github.com/peterrauscher/asyncio-task-manager
Author-email: Peter Rauscher <peter@peterrauscher.com>
License-Expression: MIT
License-File: LICENSE.txt
Classifier: Development Status :: 4 - Beta
Classifier: Programming Language :: Python
Classifier: Programming Language :: Python :: 3.8
Classifier: Programming Language :: Python :: 3.9
Classifier: Programming Language :: Python :: 3.10
Classifier: Programming Language :: Python :: 3.11
Classifier: Programming Language :: Python :: 3.12
Classifier: Programming Language :: Python :: Implementation :: CPython
Classifier: Programming Language :: Python :: Implementation :: PyPy
Requires-Python: >=3.8
